MANIFEST.in
Makefile
README
setup.py
test/__init__.py
test/__init__.pyc
test/setup_test.py
test/test_twanager.py
test/test_unicode.py
test/test_variables.py
test/test_web.py
test/test_web_redirect.py
tiddlywebplugins/__init__.py
tiddlywebplugins.urls.egg-info/PKG-INFO
tiddlywebplugins.urls.egg-info/SOURCES.txt
tiddlywebplugins.urls.egg-info/dependency_links.txt
tiddlywebplugins.urls.egg-info/namespace_packages.txt
tiddlywebplugins.urls.egg-info/requires.txt
tiddlywebplugins.urls.egg-info/top_level.txt
tiddlywebplugins/urls/__init__.py
tiddlywebplugins/urls/config.py
tiddlywebplugins/urls/handler.py
tiddlywebplugins/urls/register.py
tiddlywebplugins/urls/twanager.py
tiddlywebplugins/urls/validator.py