Metadata-Version: 1.0
Name: tiddlywebplugins.urls
Version: 0.6.1
Summary: Map TiddlyWeb URLs to your own custom URLs
Home-page: http://pypi.python.org/pypi/tiddlywebplugins.urls
Author: Ben Gillies
Author-email: bengillies@gmail.com
License: UNKNOWN
Platform: Posix; MacOS X; Windows
